investpy/__init__.py
investpy/calculos.py
investpy/dados.py
investpy/visualizacao.py
investimentpy12-1.0.3.dist-info/METADATA
investimentpy12-1.0.3.dist-info/WHEEL
investimentpy12-1.0.3.dist-info/top_level.txt
investimentpy12-1.0.3.dist-info/RECORD
