Metadata-Version: 2.4
Name: investimentpy12
Version: 1.0.3
Summary: Uma biblioteca para análise de investimentos
Home-page: https://github.com/luestevam/investimentpy12
Author: Luciana Estevam
Author-email: luesteva@gmail.com
License: MIT
Dynamic: author
Dynamic: author-email
Dynamic: description
Dynamic: description-content-type
Dynamic: home-page
Dynamic: license
Dynamic: summary
